bayesian_ab_testing/__init__.py
bayesian_ab_testing/config.py
bayesian_ab_testing/utils.py
bayesian_ab_testing/api/__init__.py
bayesian_ab_testing/api/api.py
bayesian_ab_testing/data_preparation/__init__.py
bayesian_ab_testing/data_preparation/data_generator.py
bayesian_ab_testing/data_preparation/schema.py
bayesian_ab_testing/data_preparation/sql_interactions.py
bayesian_ab_testing/logger/__init__.py
bayesian_ab_testing/logger/logger.py
bayesian_ab_testing/models/__init__.py
bayesian_ab_testing/models/TS_Bernoulli/__init__.py
bayesian_ab_testing/models/TS_Bernoulli/bernoulli_algorithm.py
bayesian_ab_testing_call_tracking/__init__.py
bayesian_ab_testing_call_tracking/utils.py
bayesian_ab_testing_call_tracking/api/__init__.py
bayesian_ab_testing_call_tracking/api/api.py
bayesian_ab_testing_call_tracking/data_preparation/__init__.py
bayesian_ab_testing_call_tracking/data_preparation/data_generator.py
bayesian_ab_testing_call_tracking/data_preparation/schema.py
bayesian_ab_testing_call_tracking/data_preparation/sql_interactions.py
bayesian_ab_testing_call_tracking/logger/__init__.py
bayesian_ab_testing_call_tracking/logger/logger.py
bayesian_ab_testing_call_tracking/models/__init__.py
bayesian_ab_testing_call_tracking/models/TS_Bernoulli/__init__.py
bayesian_ab_testing_call_tracking/models/TS_Bernoulli/bernoulli_algorithm.py
bayesian_ab_testing-1.1.2.dist-info/METADATA
bayesian_ab_testing-1.1.2.dist-info/WHEEL
bayesian_ab_testing-1.1.2.dist-info/top_level.txt
bayesian_ab_testing-1.1.2.dist-info/RECORD
